[{"date": "2017-11-13", "home_team": "Wichita State Shockers", "away_team": "Charleston Cougars", "home_score": 81, "away_score": 63}, {"date": "2017-11-13", "home_team": "Florida Gators", "away_team": "Gardner-Webb Runnin' Bulldogs", "home_score": 116, "away_score": 74}, {"date": "2017-11-13", "home_team": "USC Trojans", "away_team": "North Dakota State Bison", "home_score": 75, "away_score": 65}, {"date": "2017-11-13", "home_team": "Cincinnati Bearcats", "away_team": "Western Carolina Catamounts", "home_score": 102, "away_score": 51}, {"date": "2017-11-13", "home_team": "Saint Mary's Gaels", "away_team": "New Mexico State Aggies", "home_score": 92, "away_score": 74}, {"date": "2017-11-13", "home_team": "Baylor Bears", "away_team": "Texas A&M-Corpus Christi Islanders", "home_score": 70, "away_score": 46}]