[{"date": "2017-12-08", "home_team": "Cal State Bakersfield Roadrunners", "away_team": "Life Pacific Warriors", "home_score": 100, "away_score": 71}, {"date": "2017-12-08", "home_team": "South Dakota State Jackrabbits", "away_team": "Concordia (NE) Clippers", "home_score": 103, "away_score": 67}, {"date": "2017-12-08", "home_team": "Liberty Flames", "away_team": "Maryland Eastern Shore Hawks", "home_score": 71, "away_score": 49}, {"date": "2017-12-08", "home_team": "Bethune-Cookman Wildcats", "away_team": "Boston University Terriers", "home_score": 87, "away_score": 90}, {"date": "2017-12-08", "home_team": "Maine Black Bears", "away_team": "Dartmouth Big Green", "home_score": 66, "away_score": 73}, {"date": "2017-12-08", "home_team": "Wake Forest Demon Deacons", "away_team": "Army Black Knights", "home_score": 109, "away_score": 80}, {"date": "2017-12-08", "home_team": "Missouri State Bears", "away_team": "Hampton Pirates", "home_score": 88, "away_score": 75}, {"date": "2017-12-08", "home_team": "Oral Roberts Golden Eagles", "away_team": "Southern Nazarene Crimson Storm", "home_score": 60, "away_score": 68}, {"date": "2017-12-08", "home_team": "UC Riverside Highlanders", "away_team": "Air Force Falcons", "home_score": 67, "away_score": 48}, {"date": "2017-12-08", "home_team": "Oregon Ducks", "away_team": "Colorado State Rams", "home_score": 95, "away_score": 65}]