[{"date": "2018-11-19", "home_team": "Delaware State Hornets", "away_team": "St. Elizabeth Eagles", "home_score": 80, "away_score": 47}, {"date": "2018-11-19", "home_team": "Oakland Golden Grizzlies", "away_team": "Defiance Yellow Jackets", "home_score": 91, "away_score": 47}, {"date": "2018-11-19", "home_team": "East Tennessee State Buccaneers", "away_team": "Chicago State Cougars", "home_score": 86, "away_score": 61}, {"date": "2018-11-19", "home_team": "UNC Greensboro Spartans", "away_team": "Prairie View A&M Panthers", "home_score": 74, "away_score": 66}, {"date": "2018-11-19", "home_team": "Marshall Thundering Herd", "away_team": "North Carolina A&T Aggies", "home_score": 95, "away_score": 71}, {"date": "2018-11-19", "home_team": "Cincinnati Bearcats", "away_team": "Western Michigan Broncos", "home_score": 78, "away_score": 52}, {"date": "2018-11-19", "home_team": "Charlotte 49ers", "away_team": "Longwood Lancers", "home_score": 42, "away_score": 39}, {"date": "2018-11-19", "home_team": "Stetson Hatters", "away_team": "Robert Morris Colonials", "home_score": 72, "away_score": 81}, {"date": "2018-11-19", "home_team": "Colgate Raiders", "away_team": "Binghamton Bearcats", "home_score": 76, "away_score": 68}, {"date": "2018-11-19", "home_team": "UAlbany Great Danes", "away_team": "SUNY-Oneonta Red Dragons", "home_score": 79, "away_score": 62}, {"date": "2018-11-19", "home_team": "Massachusetts Minutemen", "away_team": "Arkansas-Pine Bluff Golden Lions", "home_score": 92, "away_score": 60}, {"date": "2018-11-19", "home_team": "Rider Broncs", "away_team": "Coppin State Eagles", "home_score": 87, "away_score": 67}, {"date": "2018-11-19", "home_team": "East Carolina Pirates", "away_team": "UT Rio Grande Valley Vaqueros", "home_score": 69, "away_score": 64}, {"date": "2018-11-19", "home_team": "Florida State Seminoles", "away_team": "Canisius Golden Griffins", "home_score": 93, "away_score": 61}, {"date": "2018-11-19", "home_team": "Rutgers Scarlet Knights", "away_team": "Eastern Michigan Eagles", "home_score": 63, "away_score": 36}, {"date": "2018-11-19", "home_team": "Detroit Mercy Titans", "away_team": "Loyola Maryland Greyhounds", "home_score": 91, "away_score": 63}, {"date": "2018-11-19", "home_team": "Charleston Southern Buccaneers", "away_team": "Trinity College of Jacksonville Eagles", "home_score": 98, "away_score": 49}, {"date": "2018-11-19", "home_team": "Lamar Cardinals", "away_team": "Arlington Baptist Patriots", "home_score": 105, "away_score": 40}, {"date": "2018-11-19", "home_team": "Oral Roberts Golden Eagles", "away_team": "Ecclesia Royals", "home_score": 109, "away_score": 72}, {"date": "2018-11-19", "home_team": "Southern Illinois Salukis", "away_team": "Howard Bison", "home_score": 83, "away_score": 69}, {"date": "2018-11-19", "home_team": "South Alabama Jaguars", "away_team": "Southeast Missouri State Redhawks", "home_score": 79, "away_score": 58}, {"date": "2018-11-19", "home_team": "Tulsa Golden Hurricane", "away_team": "Little Rock Trojans", "home_score": 88, "away_score": 78}, {"date": "2018-11-19", "home_team": "Houston Cougars", "away_team": "Northwestern State Demons", "home_score": 82, "away_score": 55}, {"date": "2018-11-19", "home_team": "Vanderbilt Commodores", "away_team": "Liberty Flames", "home_score": 79, "away_score": 70}, {"date": "2018-11-19", "home_team": "North Carolina Tar Heels", "away_team": "Saint Francis Red Flash", "home_score": 101, "away_score": 76}, {"date": "2018-11-19", "home_team": "UTEP Miners", "away_team": "Eastern New Mexico Greyhounds", "home_score": 66, "away_score": 59}, {"date": "2018-11-19", "home_team": "Washington State Cougars", "away_team": "Cal Poly Mustangs", "home_score": 84, "away_score": 70}, {"date": "2018-11-19", "home_team": "Idaho State Bengals", "away_team": "Bethesda Flames", "home_score": 115, "away_score": 60}, {"date": "2018-11-19", "home_team": "Nevada Wolf Pack", "away_team": "California Baptist Lancers", "home_score": 90, "away_score": 55}, {"date": "2018-11-19", "home_team": "Portland Pilots", "away_team": "Lewis & Clark Pioneers", "home_score": 77, "away_score": 57}, {"date": "2018-11-19", "home_team": "UCLA Bruins", "away_team": "Presbyterian Blue Hose", "home_score": 80, "away_score": 65}]